geomux/__init__.py
geomux/__main__.py
geomux/geomux.py
geomux/mixture.py
geomux/utils.py
geomux-0.5.5.dist-info/licenses/LICENSE
geomux-0.5.5.dist-info/METADATA
geomux-0.5.5.dist-info/WHEEL
geomux-0.5.5.dist-info/entry_points.txt
geomux-0.5.5.dist-info/top_level.txt
geomux-0.5.5.dist-info/RECORD
