Metadata-Version: 2.4
Name: geomux
Version: 0.5.5
Summary: A tool to assign identifiers to cell barcodes
Author: Noam Teyssier
Requires-Python: >=3.10
License-File: LICENSE
Requires-Dist: anndata>=0.10.9
Requires-Dist: joblib>=1.5.2
Requires-Dist: numpy>=2.1.1
Requires-Dist: polars>=1.33.1
Requires-Dist: pyarrow>=21.0.0
Requires-Dist: scikit-learn>=1.7.2
Requires-Dist: scipy>=1.14.1
Requires-Dist: threadpoolctl>=3.6.0
Requires-Dist: typer>=0.16.0
Dynamic: license-file
